gslackers/__init__.py
gslackers/hooks.py
gslackers/models.py
gslackers/py.typed
gslackers/registry.py
gslackers/server.py
gslackers/verification.py
gslackers-1.0.4.dist-info/LICENSE
gslackers-1.0.4.dist-info/METADATA
gslackers-1.0.4.dist-info/WHEEL
gslackers-1.0.4.dist-info/RECORD
