Metadata-Version: 2.1
Name: gslackers
Version: 1.0.4
Summary: Slack webhooks API served by FastAPI
Home-page: https://github.com/grishjan/slackers
License: MIT
Author: Niels van Huijstee
Author-email: niels@huijs.net
Requires-Python: >=3.7,<4.0
Classifier: Development Status :: 5 - Production/Stable
Classifier: Environment :: Web Environment
Classifier: Intended Audience :: Developers
Classifier: License :: OSI Approved :: MIT License
Classifier: Programming Language :: Python :: 3
Classifier: Programming Language :: Python :: 3.7
Classifier: Programming Language :: Python :: 3.8
Classifier: Programming Language :: Python :: 3.9
Classifier: Programming Language :: Python :: 3.10
Classifier: Programming Language :: Python :: 3.11
Classifier: Topic :: Communications :: Chat
Classifier: Topic :: Office/Business
Provides-Extra: uvicorn
Requires-Dist: fastapi (>=0,<1)
Requires-Dist: pyee (>=6.0,<7.0)
Requires-Dist: python-multipart (>=0.0.5,<0.0.6)
Requires-Dist: requests (>=2.22,<3.0)
Project-URL: Repository, https://github.com/grishjan/slackers
